setup.py
cvauto/__init__.py
cvauto/auto.py
cvauto/position.py
cvauto/tools.py
cvauto.egg-info/PKG-INFO
cvauto.egg-info/SOURCES.txt
cvauto.egg-info/dependency_links.txt
cvauto.egg-info/not-zip-safe
cvauto.egg-info/requires.txt
cvauto.egg-info/top_level.txt