Metadata-Version: 1.0
Name: cvauto
Version: 0.0.4
Summary: It's a gui automation pkg, and base on opencv, just a simple picture match.
Home-page: https://github.com/pysrc/cvauto
Author: L.Chen
Author-email: 1570184051@qq.com
License: MIT
Keywords: automation,GUI,opencv,rpa
Platform: any
